{
  "device": "openaps://dougstamper", 
  "pump": {
    "battery": {
      "status": "normal", 
      "voltage": 1.41
    }, 
    "status": {
      "status": "normal", 
      "timestamp": "2016-06-14T08:28:59.000Z", 
      "bolusing": false, 
      "suspended": false
    }, 
    "reservoir": 45.1, 
    "clock": "2016-06-14T04:28:24-04:00"
  }, 
  "openaps": {
    "suggested": {
      "bg": 129, 
      "temp": "absolute", 
      "snoozeBG": 172, 
      "timestamp": "2016-06-14T08:29:16.000Z", 
      "predBGs": {
        "IOB": [
          129, 
          128, 
          127, 
          125, 
          124, 
          122, 
          121, 
          119, 
          116, 
          114, 
          112, 
          109, 
          106, 
          103, 
          100, 
          97, 
          93, 
          90, 
          87, 
          83, 
          81, 
          78, 
          75, 
          73, 
          71, 
          69, 
          67, 
          65, 
          64, 
          63, 
          61, 
          60, 
          60, 
          59, 
          58
        ]
      }, 
      "reason": "COB: 0, Dev: 39, BGI: -0.84, ISF: 56.1, Target: 93; Eventual BG 113>=97, temp 1 >~ req 0.68U/hr", 
      "COB": 0, 
      "eventualBG": 113, 
      "tick": -1, 
      "IOB": 0.989
    }, 
    "iob": [
      {
        "netbasalinsulin": 0.5, 
        "hightempinsulin": 0.65, 
        "basaliob": 0.29, 
        "time": "2016-06-14T08:28:24.000Z", 
        "bolussnooze": 0.699, 
        "activity": 0.003, 
        "iob": 0.989
      }, 
      {
        "netbasalinsulin": 0.55, 
        "hightempinsulin": 0.7, 
        "basaliob": 0.324, 
        "time": "2016-06-14T08:33:24.000Z", 
        "bolussnooze": 0.666, 
        "activity": 0.0036, 
        "iob": 1.021
      }, 
      {
        "netbasalinsulin": 0.7, 
        "hightempinsulin": 0.8, 
        "basaliob": 0.409, 
        "time": "2016-06-14T08:38:24.000Z", 
        "bolussnooze": 0.591, 
        "activity": 0.0042, 
        "iob": 1.1
      }, 
      {
        "netbasalinsulin": 0.75, 
        "hightempinsulin": 0.85, 
        "basaliob": 0.443, 
        "time": "2016-06-14T08:43:24.000Z", 
        "bolussnooze": 0.476, 
        "activity": 0.0048, 
        "iob": 1.126
      }, 
      {
        "netbasalinsulin": 0.8, 
        "hightempinsulin": 0.9, 
        "basaliob": 0.477, 
        "time": "2016-06-14T08:48:24.000Z", 
        "bolussnooze": 0.328, 
        "activity": 0.0054, 
        "iob": 1.149
      }, 
      {
        "netbasalinsulin": 0.7, 
        "hightempinsulin": 0.8, 
        "basaliob": 0.46, 
        "time": "2016-06-14T08:53:24.000Z", 
        "bolussnooze": 0.204, 
        "activity": 0.006, 
        "iob": 1.119
      }, 
      {
        "netbasalinsulin": 0.7, 
        "hightempinsulin": 0.8, 
        "basaliob": 0.443, 
        "time": "2016-06-14T08:58:24.000Z", 
        "bolussnooze": 0.108, 
        "activity": 0.0067, 
        "iob": 1.085
      }, 
      {
        "netbasalinsulin": 0.65, 
        "hightempinsulin": 0.75, 
        "basaliob": 0.425, 
        "time": "2016-06-14T09:03:24.000Z", 
        "bolussnooze": 0.043, 
        "activity": 0.0073, 
        "iob": 1.049
      }, 
      {
        "netbasalinsulin": 0.65, 
        "hightempinsulin": 0.75, 
        "basaliob": 0.406, 
        "time": "2016-06-14T09:08:24.000Z", 
        "bolussnooze": 0.007, 
        "activity": 0.008, 
        "iob": 1.009
      }, 
      {
        "netbasalinsulin": 0.7, 
        "hightempinsulin": 0.75, 
        "basaliob": 0.386, 
        "time": "2016-06-14T09:13:24.000Z", 
        "bolussnooze": 0, 
        "activity": 0.0087, 
        "iob": 0.965
      }, 
      {
        "netbasalinsulin": 0.7, 
        "hightempinsulin": 0.75, 
        "basaliob": 0.365, 
        "time": "2016-06-14T09:18:24.000Z", 
        "bolussnooze": 0, 
        "activity": 0.0094, 
        "iob": 0.918
      }, 
      {
        "netbasalinsulin": 0.7, 
        "hightempinsulin": 0.75, 
        "basaliob": 0.343, 
        "time": "2016-06-14T09:23:24.000Z", 
        "bolussnooze": 0, 
        "activity": 0.0102, 
        "iob": 0.867
      }, 
      {
        "netbasalinsulin": 0.7, 
        "hightempinsulin": 0.75, 
        "basaliob": 0.321, 
        "time": "2016-06-14T09:28:24.000Z", 
        "bolussnooze": 0, 
        "activity": 0.0108, 
        "iob": 0.813
      }, 
      {
        "netbasalinsulin": 0.65, 
        "hightempinsulin": 0.7, 
        "basaliob": 0.298, 
        "time": "2016-06-14T09:33:24.000Z", 
        "bolussnooze": 0, 
        "activity": 0.0114, 
        "iob": 0.756
      }, 
      {
        "netbasalinsulin": 0.6, 
        "hightempinsulin": 0.65, 
        "basaliob": 0.274, 
        "time": "2016-06-14T09:38:24.000Z", 
        "bolussnooze": 0, 
        "activity": 0.012, 
        "iob": 0.695
      }, 
      {
        "netbasalinsulin": 0.6, 
        "hightempinsulin": 0.65, 
        "basaliob": 0.25, 
        "time": "2016-06-14T09:43:24.000Z", 
        "bolussnooze": 0, 
        "activity": 0.0124, 
        "iob": 0.633
      }, 
      {
        "netbasalinsulin": 0.6, 
        "hightempinsulin": 0.65, 
        "basaliob": 0.227, 
        "time": "2016-06-14T09:48:24.000Z", 
        "bolussnooze": 0, 
        "activity": 0.012, 
        "iob": 0.573
      }, 
      {
        "netbasalinsulin": 0.6, 
        "hightempinsulin": 0.65, 
        "basaliob": 0.204, 
        "time": "2016-06-14T09:53:24.000Z", 
        "bolussnooze": 0, 
        "activity": 0.0115, 
        "iob": 0.515
      }, 
      {
        "netbasalinsulin": 0.6, 
        "hightempinsulin": 0.65, 
        "basaliob": 0.182, 
        "time": "2016-06-14T09:58:24.000Z", 
        "bolussnooze": 0, 
        "activity": 0.011, 
        "iob": 0.46
      }, 
      {
        "netbasalinsulin": 0.6, 
        "hightempinsulin": 0.65, 
        "basaliob": 0.162, 
        "time": "2016-06-14T10:03:24.000Z", 
        "bolussnooze": 0, 
        "activity": 0.0103, 
        "iob": 0.409
      }, 
      {
        "netbasalinsulin": 0.55, 
        "hightempinsulin": 0.6, 
        "basaliob": 0.143, 
        "time": "2016-06-14T10:08:24.000Z", 
        "bolussnooze": 0, 
        "activity": 0.0096, 
        "iob": 0.361
      }, 
      {
        "netbasalinsulin": 0.55, 
        "hightempinsulin": 0.6, 
        "basaliob": 0.126, 
        "time": "2016-06-14T10:13:24.000Z", 
        "bolussnooze": 0, 
        "activity": 0.009, 
        "iob": 0.316
      }, 
      {
        "netbasalinsulin": 0.5, 
        "hightempinsulin": 0.55, 
        "basaliob": 0.11, 
        "time": "2016-06-14T10:18:24.000Z", 
        "bolussnooze": 0, 
        "activity": 0.0083, 
        "iob": 0.274
      }, 
      {
        "netbasalinsulin": 0.45, 
        "hightempinsulin": 0.5, 
        "basaliob": 0.095, 
        "time": "2016-06-14T10:23:24.000Z", 
        "bolussnooze": 0, 
        "activity": 0.0077, 
        "iob": 0.236
      }, 
      {
        "netbasalinsulin": 0.4, 
        "hightempinsulin": 0.45, 
        "basaliob": 0.081, 
        "time": "2016-06-14T10:28:24.000Z", 
        "bolussnooze": 0, 
        "activity": 0.0071, 
        "iob": 0.2
      }, 
      {
        "netbasalinsulin": 0.4, 
        "hightempinsulin": 0.45, 
        "basaliob": 0.069, 
        "time": "2016-06-14T10:33:24.000Z", 
        "bolussnooze": 0, 
        "activity": 0.0065, 
        "iob": 0.168
      }, 
      {
        "netbasalinsulin": 0.4, 
        "hightempinsulin": 0.45, 
        "basaliob": 0.057, 
        "time": "2016-06-14T10:38:24.000Z", 
        "bolussnooze": 0, 
        "activity": 0.0059, 
        "iob": 0.138
      }, 
      {
        "netbasalinsulin": 0.4, 
        "hightempinsulin": 0.45, 
        "basaliob": 0.047, 
        "time": "2016-06-14T10:43:24.000Z", 
        "bolussnooze": 0, 
        "activity": 0.0054, 
        "iob": 0.111
      }, 
      {
        "netbasalinsulin": 0.4, 
        "hightempinsulin": 0.45, 
        "basaliob": 0.038, 
        "time": "2016-06-14T10:48:24.000Z", 
        "bolussnooze": 0, 
        "activity": 0.0048, 
        "iob": 0.087
      }, 
      {
        "netbasalinsulin": 0.4, 
        "hightempinsulin": 0.45, 
        "basaliob": 0.029, 
        "time": "2016-06-14T10:53:24.000Z", 
        "bolussnooze": 0, 
        "activity": 0.0042, 
        "iob": 0.066
      }, 
      {
        "netbasalinsulin": 0.45, 
        "hightempinsulin": 0.45, 
        "basaliob": 0.022, 
        "time": "2016-06-14T10:58:24.000Z", 
        "bolussnooze": 0, 
        "activity": 0.0036, 
        "iob": 0.048
      }, 
      {
        "netbasalinsulin": 0.45, 
        "hightempinsulin": 0.45, 
        "basaliob": 0.016, 
        "time": "2016-06-14T11:03:24.000Z", 
        "bolussnooze": 0, 
        "activity": 0.003, 
        "iob": 0.033
      }, 
      {
        "netbasalinsulin": 0.45, 
        "hightempinsulin": 0.45, 
        "basaliob": 0.011, 
        "time": "2016-06-14T11:08:24.000Z", 
        "bolussnooze": 0, 
        "activity": 0.0024, 
        "iob": 0.021
      }, 
      {
        "netbasalinsulin": 0.35, 
        "hightempinsulin": 0.35, 
        "basaliob": 0.007, 
        "time": "2016-06-14T11:13:24.000Z", 
        "bolussnooze": 0, 
        "activity": 0.0018, 
        "iob": 0.012
      }, 
      {
        "netbasalinsulin": 0.35, 
        "hightempinsulin": 0.35, 
        "basaliob": 0.004, 
        "time": "2016-06-14T11:18:24.000Z", 
        "bolussnooze": 0, 
        "activity": 0.0013, 
        "iob": 0.006
      }, 
      {
        "netbasalinsulin": 0.3, 
        "hightempinsulin": 0.3, 
        "basaliob": 0.002, 
        "time": "2016-06-14T11:23:24.000Z", 
        "bolussnooze": 0, 
        "activity": 0.0007, 
        "iob": 0.002
      }
    ], 
    "enacted": {
      "bg": 130, 
      "temp": "absolute", 
      "snoozeBG": 166, 
      "recieved": true, 
      "predBGs": {
        "IOB": [
          130, 
          137, 
          143, 
          149, 
          154, 
          158, 
          161, 
          164, 
          166, 
          167, 
          167, 
          167, 
          166, 
          165, 
          164, 
          163, 
          162, 
          161, 
          160, 
          159, 
          159, 
          158, 
          157, 
          156, 
          156, 
          155, 
          155, 
          154, 
          154, 
          154, 
          153, 
          153, 
          153, 
          153, 
          152
        ]
      }, 
      "reason": "COB: 0, Dev: 51, BGI: -0.81, ISF: 57.7, Target: 94; Eventual BG 166>=98, adj. req. rate:2.8 to maxSafeBasal:1.0, temp 0.65<1.0U/hr", 
      "rate": 1, 
      "COB": 0, 
      "eventualBG": 166, 
      "timestamp": "2016-06-14T08:21:25.000Z", 
      "duration": 30, 
      "tick": "+18", 
      "IOB": 0.262
    }
  }
}